MANIFEST.in
README.rst
setup.py
c2c/__init__.py
c2c.recipe.cssmin.egg-info/PKG-INFO
c2c.recipe.cssmin.egg-info/SOURCES.txt
c2c.recipe.cssmin.egg-info/dependency_links.txt
c2c.recipe.cssmin.egg-info/entry_points.txt
c2c.recipe.cssmin.egg-info/namespace_packages.txt
c2c.recipe.cssmin.egg-info/requires.txt
c2c.recipe.cssmin.egg-info/top_level.txt
c2c/recipe/__init__.py
c2c/recipe/cssmin/__init__.py
c2c/recipe/cssmin/buildout.py