Metadata-Version: 1.0
Name: c2c.recipe.cssmin
Version: 0.6
Summary: A buildout recipe to merge and compress css files
Home-page: https://github.com/camptocamp/c2c.recipe.cssmin
Author: Frederic Junod
Author-email: frederic.junod@camptocamp.com
License: MIT License
Platform: UNKNOWN
Classifier: Framework :: Buildout
Classifier: Intended Audience :: Developers
Classifier: Topic :: Software Development :: Build Tools
Classifier: Topic :: Software Development :: Libraries :: Python Modules
Classifier: License :: OSI Approved :: MIT License
